docker_parser/__init__.py
docker_parser/bashlex_utils.py
docker_parser/classess.py
docker_parser/dependencies.py
docker_parser/parser.py
docker_parser-0.0.8.dist-info/METADATA
docker_parser-0.0.8.dist-info/WHEEL
docker_parser-0.0.8.dist-info/licenses/LICENSE
docker_parser-0.0.8.dist-info/RECORD
