Metadata-Version: 2.1
Name: docker-parser
Version: 0.0.8
Summary: package parsing docker files
Project-URL: Homepage, https://gitlab.fi.muni.cz/cybersec/verp/dockerfile-parser
Author-email: Ivan Mitruk <ivan@mitruk.eu>
License-File: LICENSE
Classifier: License :: OSI Approved :: MIT License
Classifier: Operating System :: OS Independent
Classifier: Programming Language :: Python :: 3
Requires-Python: >=3.7
Requires-Dist: bashlex
Requires-Dist: docker
